workadays/__init__.py
workadays/argentina.py
workadays/brazil.py
workadays/constants.py
workadays/countries.py
workadays/holiday_base.py
workadays/holidays.py
workadays/luxembourg.py
workadays/main.py
workadays/united_kingdom.py
workadays/united_states.py
workadays/workdays.py
workadays/workdays_tests.py
workadays-2023.12.30.dist-info/LICENSE
workadays-2023.12.30.dist-info/METADATA
workadays-2023.12.30.dist-info/WHEEL
workadays-2023.12.30.dist-info/top_level.txt
workadays-2023.12.30.dist-info/RECORD
