Metadata-Version: 2.1
Name: workadays
Version: 2023.12.30
Summary: Calendário de dias úteis, dias corridos e dias 360 (30/360).
Home-page: https://github.com/mfhorita
Author: Marcelo Horita
Author-email: mfhorita@gmail.com.br
License: MIT License
Keywords: workdays workadays feriados holidays diasuteis uteis,dias360,days360,days
Classifier: License :: Freeware
Classifier: Programming Language :: Python
Classifier: Operating System :: OS Independent
Classifier: Development Status :: 5 - Production/Stable
Classifier: Natural Language :: Portuguese (Brazilian)
Classifier: Intended Audience :: Developers
Classifier: Topic :: Utilities
License-File: LICENSE
Requires-Dist: python-dateutil (>=2.8.0)
Requires-Dist: six (>=1.11.0)
